pybtm/main.py
pybottom-0.1.0.dist-info/METADATA
pybottom-0.1.0.dist-info/WHEEL
pybottom-0.1.0.dist-info/entry_points.txt
pybottom-0.1.0.dist-info/top_level.txt
pybottom-0.1.0.dist-info/RECORD
