Metadata-Version: 2.4
Name: pybottom
Version: 0.1.0
Summary: A cross-platform interactive process monitor (like top) using psutil and rich.
Classifier: Programming Language :: Python :: 3
Requires-Python: >=3.8
Requires-Dist: psutil>=5.9.0
Requires-Dist: rich>=13.0.0
